[
    {
        "rows": [
            [
                {
                    "name": "actief"
                },
                {
                    "name": "herbalifeID"
                },
                {
                    "name": "herbalifePin"
                }
            ],
            [
                {
                    "name": "name"
                }
            ],
            [
                {
                    "name": "sponser"
                }
            ]
        ],
        "style": "default",
        "label": "Overview"
    },
    {
        "rows": [
            [
                {
                    "name": "maxCallAttempts"
                }
            ]
        ],
        "dynamicLogicVisible": null,
        "style": "default",
        "tabBreak": true,
        "tabLabel": "Config",
        "hidden": false,
        "noteText": null,
        "noteStyle": "info",
        "customLabel": "Configuratie"
    }
]