[
    {
        "rows": [
            [
                {
                    "name": "name"
                },
                {
                    "name": "number"
                }
            ],
            [
                {
                    "name": "status"
                },
                {
                    "name": "type"
                }
            ],
            [
                {
                    "name": "priority"
                },
                false
            ],
            [
                {
                    "name": "lead"
                },
                {
                    "name": "contact"
                }
            ],
            [
                {
                    "name": "description"
                }
            ],
            [
                {
                    "name": "attachments"
                }
            ]
        ],
        "style": "default",
        "label": ""
    }
]