{
    "collection": {
        "countDisabled": false
    },
    "fields": {
        "status": {
            "options": [
                "New",
                "Assigned",
                "Pending",
                "ToBeDiscussed",
                "Blocked",
                "Closed",
                "Rejected",
                "Duplicate"
            ],
            "style": {
                "New": null,
                "Assigned": "primary",
                "Pending": "warning",
                "ToBeDiscussed": "warning",
                "Blocked": "danger",
                "Closed": "success",
                "Rejected": "info",
                "Duplicate": "info"
            },
            "required": true,
            "isSorted": false
        },
        "type": {
            "options": [
                "",
                "Question",
                "Problem",
                "Idea"
            ],
            "style": {
                "": null,
                "Question": "info",
                "Problem": "danger",
                "Idea": null
            }
        }
    }
}